{
	"BugBounty":{
		"Hackerone":{
			"title":"Hackerone hacktivity",
			"rss":"https://rsshub.app/hackerone/hacktivity"
		}
	},
	"blogs":{
		"infosecwriteups.com" : {
			"title":"InfoSec writeups",
			"rss": "https://infosecwriteups.com/feed"
		},
		"sonarsource":{
			"title":"Sonar Blog",
			"rss":"https://www.sonarsource.com/rss.xml"
		},
		"assetnote":{
			"title":"Assetnote Blog",
			"rss":"https://blog.assetnote.io/feed.xml"
		},
		"ptswarm":{
			"title":"PTSWARM Blog",
			"rss":"https://swarm.ptsecurity.com/feed/"
		},
		"seebug":{
			"title":"Seebug Paper",
			"rss":"https://paper.seebug.org/rss/"
		},
		"watchtowr":{
			"title":"watchTowr Labs",
			"rss":"https://labs.watchtowr.com/rss/"
		},
		"soroush.me":{
			"title":"Soroush Dalili (@irsdl) Blog",
			"rss":"https://soroush.me/blog/feed/"
		},
		"gosecure":{
			"title":"GoSecure Blog",
			"rss":"https://www.gosecure.net/feed/"
		},
		"frycos.github.io":{
			"title":"Frycos Security Diary",
			"rss":"https://frycos.github.io/feed.xml"
		},
		"githubsec":{
			"title":"Github Security",
			"rss":"https://github.blog/category/security/feed/"
		},
		"zdi":{
			"title":"Zeroday Initiative",
			"rss":"https://www.zerodayinitiative.com/blog/?format=rss"
		},
		"portswigger": {
			"title":"PortSwigger Research",
			"rss":"https://portswigger.net/research/rss"
		},
		"n00pyBlog":{
			"title":"N00PY BLOG",
			"rss":"https://www.n00py.io/feed/"
		},
		"redditnetsec":{
			"title":"Reddit /r/netsec",
			"rss":"https://www.reddit.com/r/netsec/.rss"
		},
		"talosintelligence":{
			"title":"Cisco Talos Blog",
			"rss":"https://blog.talosintelligence.com/rss/"
		},
		"mobilehacker":{
			"title":"mobile hacker",
			"rss":"https://www.mobile-hacker.com/feed/"
		},
		"code-white":{
			"title":"Blog on CODE WHITE",
			"rss":"https://code-white.com/blog/index.xml"
		},
		"nccgroupresearch":{
			"title":"NCC Research Blog",
			"rss":"https://research.nccgroup.com/feed/"
		},
		"volexity":{
			"title":"Volexity Blog",
			"rss":"https://www.volexity.com/blog/feed/"
		},
		"srcincite":{
			"title":"srcincite.io blog",
			"rss":"https://srcincite.io/feed.xml"
		},
		"redditwebsecurityresearch":{
			"title":"Reddit /r/websecurityresearch",
			"rss":"https://www.reddit.com/r/websecurityresearch/.rss"
		},
		"shielderblog":{
			"title":"Blog on Shielder",
			"rss":"https://www.shielder.com/blog/index.xml"
		},
		"shielderadvisories":{
			"title":"Advisories on Shielder",
			"rss":"https://www.shielder.com/advisories/index.xml"
		},
		"assetnoteresearch":{
			"title":"Assetnote Research",
			"rss":"https://www.assetnote.io/research/rss.xml"
		},
		"horizon3redteam":{
			"title":"Horizon3.ai Red Team",
			"rss":"https://www.horizon3.ai/category/blog/red-team/feed/"
		},
		"synacktivBlog":{
			"title":"Synacktiv",
			"rss":"https://www.synacktiv.com/feed/lastblog.xml"
		},
		"starlabsBlog":{
			"title":"Blogs on STAR Labs",
			"rss":"https://starlabs.sg/blog/index.xml"
		}
	},
	"cve":
	{
		"zdipubadv":{
			"title":"ZDI: Published Advisories",
			"rss":"https://www.zerodayinitiative.com/rss/published/"
		},
		"zdiupcomingadv":{
			"title":"ZDI: Upcoming Advisories",
			"rss":"https://www.zerodayinitiative.com/rss/upcoming/"
		},
		"cve.org":{
			"title":"cve.org",
			"rss":"https://raw.githubusercontent.com/websecnews/websecnews.github.io/main/cve_rss.xml"
		}
		
	},
	"advisories":
	{
		"vmwareadvi":{
			"title":"VMware Security Advisory",
			"rss":"https://www.vmware.com/security/advisories.xml"
		},
		"microsoftadvi":{
			"title":"MSRC Security Advisory",
			"rss":"https://api.msrc.microsoft.com/update-guide/rss"
		},
		"f5advi":{
			"title":"F5 Security Advisory",
			"rss":"https://support.apis.f5.com/articles/rss/v4/feed?apikey=aIy8F8CUfdgqXPv6pHJ0RU64GQiYiyUK&page=1&results=10&source=kbarticles&source=techcomm&documentType=Security%20Advisory&firstPublishedDateStart=2023-10-26&requestid=db908a17-2f2d-4bd6-9c17-22a73e01b505"
		},
		"starlabsadvi":{
			"title":"Advisories on STAR Labs",
			"rss":"https://starlabs.sg/advisories/index.xml"
		},
		"shielderadvi":{
			"title":"Advisories on Shielder",
			"rss":"https://www.shielder.com/advisories/index.xml"
		},
		"ciscoadvi":{
			"title":"Cisco Security Advisory",
			"rss":"https://sec.cloudapps.cisco.com/security/center/psirtrss20/CiscoSecurityAdvisory.xml"
		},
		"fortiguardadvi":{
			"title":"FortiGuard Labs Advisory",
			"rss":"https://filestore.fortinet.com/fortiguard/rss/ir.xml"
		},
		"paloaltonetworksadvi":{
			"title":"Palo Alto Networks Security Advisories",
			"rss":"https://security.paloaltonetworks.com/rss.xml"
		},
		"splunkdvi":{
			"title":"Splunk Security Announcements",
			"rss":"https://advisory.splunk.com/feed.xml"
		},
		"drupaladvi":{
			"title":"Drupal Security Advisories",
			"rss":"https://www.drupal.org/security/rss.xml"
		},
		"jenkinsadvi":{
			"title":"Jenkins Security Advisories",
			"rss":"https://www.jenkins.io/security/advisories/rss.xml"
		},
		"ubuntuadvi":{
			"title":"Ubuntu Security Notices",
			"rss":"https://ubuntu.com/security/notices/rss.xml"
		},
		"typo3advi":{
			"title":"Typo3 Security Advisories",
			"rss":"https://typo3.org/?type=101"
		},
		"sonicwalladvi":{
			"title":"SonicWall Security Advisories",
			"rss":"https://psirtapi.global.sonicwall.com/api/v1/feed/rss.xml"
		},
		"ghsecuritylabadvi":{
			"title":"GitHub Security Lab | Advisories",
			"rss":"https://securitylab.github.com/advisories/feed.xml"
		}
		
		
	}
}
