{
    "InfoSec writeups": [
        {
            "entry": {
                "link": "https://infosecwriteups.com/how-to-get-pwned-with-extra-index-url-44b04b52913a?source=rss----7b722bfd1b8d---4",
                "title": "How to get pwned with\u200a\u2014\u200aextra-index-url"
            },
            "fetchDate": "2025-12-27 04:55:33.437186"
        },
        {
            "entry": {
                "link": "https://infosecwriteups.com/intercepting-custom-links-in-ios-apps-e3023794d507?source=rss----7b722bfd1b8d---4",
                "title": "iOS apps security \u2014 Intercepting custom deeplinks for security testing."
            },
            "fetchDate": "2025-12-27 04:55:33.437186"
        },
        {
            "entry": {
                "link": "https://infosecwriteups.com/from-login-form-to-root-access-chaining-sqli-ssti-for-total-compromise-11c77f0d3539?source=rss----7b722bfd1b8d---4",
                "title": "From Login Form to Root Access: Chaining SQLi & SSTI for Total Compromise"
            },
            "fetchDate": "2025-12-27 04:55:33.437186"
        },
        {
            "entry": {
                "link": "https://infosecwriteups.com/how-data-travels-packet-switching-vs-circuit-switching-f097ca6e2d9b?source=rss----7b722bfd1b8d---4",
                "title": "How Data Travels: Packet Switching vs Circuit Switching"
            },
            "fetchDate": "2025-12-27 04:55:33.437186"
        },
        {
            "entry": {
                "link": "https://infosecwriteups.com/bankgpt-tryhackme-writeup-walkthrough-e5457594887b?source=rss----7b722bfd1b8d---4",
                "title": "BankGPT TryHackMe Writeup Walkthrough"
            },
            "fetchDate": "2025-12-27 04:55:33.437186"
        },
        {
            "entry": {
                "link": "https://infosecwriteups.com/i-didnt-hack-you-you-posted-everything-4d6bae509815?source=rss----7b722bfd1b8d---4",
                "title": "I Didn\u2019t Hack You. You Posted Everything."
            },
            "fetchDate": "2025-12-27 04:55:33.437186"
        },
        {
            "entry": {
                "link": "https://infosecwriteups.com/100-bounty-xss-input-validation-1ccfb35c5e1f?source=rss----7b722bfd1b8d---4",
                "title": "$100 bounty\u200a\u2014\u200aXSS & Input Validation"
            },
            "fetchDate": "2025-12-27 04:55:33.437186"
        }
    ]
}