{
    "Cisco Talos Blog": [
        {
            "entry": {
                "link": "https://blog.talosintelligence.com/vulnerability-roundup-may-1-2024/",
                "title": "Vulnerabilities in employee management system could lead to remote code execution, login credential theft"
            },
            "fetchDate": "2024-05-01 16:00:28.510429"
        }
    ],
    "InfoSec writeups": [
        {
            "entry": {
                "link": "https://infosecwriteups.com/aws-s3-bucket-misconfiguration-exposes-pii-and-documents-of-job-seekers-7b1332b0ecf1?source=rss----7b722bfd1b8d---4",
                "title": "AWS S3 Bucket Misconfiguration Exposes PII and Documents of Job Seekers"
            },
            "fetchDate": "2024-05-01 15:40:27.704769"
        }
    ],
    "Reddit /r/netsec": [
        {
            "entry": {
                "link": "https://www.reddit.com/r/netsec/comments/1chpzlc/5_methods_i_use_to_discover_apis/",
                "title": "5 Methods I Use To Discover APIs"
            },
            "fetchDate": "2024-05-01 16:24:16.581412"
        },
        {
            "entry": {
                "link": "https://www.reddit.com/r/netsec/comments/1chn4l1/front_porch_digital_forensics_trap_beats_open/",
                "title": "Front Porch Digital Forensics - Trap beats, open loops and Dirty Daves spell trouble for our forensicators."
            },
            "fetchDate": "2024-05-01 14:12:57.950304"
        }
    ],
    "Reddit /r/websecurityresearch": [
        {
            "entry": {
                "link": "https://www.reddit.com/r/websecurityresearch/comments/1chl5fn/mxss_cheatsheet/",
                "title": "mXSS cheatsheet"
            },
            "fetchDate": "2024-05-01 12:53:33.464418"
        }
    ],
    "Sonar Blog": [
        {
            "entry": {
                "link": "https://www.sonarsource.com/blog/leveraging-sonarqube-sonarcloud-and-sonarlint-for-effective-shift-left-practices",
                "title": "Leveraging SonarQube, SonarCloud, and SonarLint for Effective Shift Left Practices"
            },
            "fetchDate": "2024-05-01 20:26:16.776120"
        }
    ]
}