{
    "InfoSec writeups": [
        {
            "entry": {
                "link": "https://infosecwriteups.com/how-to-fix-blue-screen-of-death-bsod-and-recover-lost-data-b5d65ace40f8?source=rss----7b722bfd1b8d---4",
                "title": "How to Fix Blue Screen of Death (BSoD) and Recover Lost Data?"
            },
            "fetchDate": "2025-01-23 10:43:15.953904"
        },
        {
            "entry": {
                "link": "https://infosecwriteups.com/5-steps-to-crafting-a-reverse-shell-plugin-in-wordpress-oscp-rce-tactics-for-beginners-07303c4e8821?source=rss----7b722bfd1b8d---4",
                "title": "5 Steps to Crafting a Reverse Shell Plugin in WordPress [OSCP RCE Tactics for Beginners]"
            },
            "fetchDate": "2025-01-23 07:41:11.365519"
        }
    ],
    "Reddit /r/netsec": [
        {
            "entry": {
                "link": "https://www.reddit.com/r/netsec/comments/1i7r9ay/role_of_cryptography_in_protecting_personal_data/",
                "title": "Role of cryptography in protecting personal data"
            },
            "fetchDate": "2025-01-23 00:59:51.366240"
        }
    ],
    "Zeroday Initiative": [
        {
            "entry": {
                "link": "https://www.thezdi.com/blog/2025/1/22/pwn2own-automotive-2025-day-two-results",
                "title": "Pwn2Own Automotive 2025 - Day Two Results"
            },
            "fetchDate": "2025-01-23 03:47:21.423767"
        }
    ]
}