{
    "Reddit /r/netsec": [
        {
            "entry": {
                "link": "https://www.reddit.com/r/netsec/comments/1ekj5by/kerberos_opsec_offense_detection_strategies_for/",
                "title": "Kerberos OPSEC: Offense & Detection Strategies for Red and Blue Team - Part 2 : AS REP Roasting"
            },
            "fetchDate": "2024-08-05 09:18:46.939608"
        },
        {
            "entry": {
                "link": "https://www.reddit.com/r/netsec/comments/1ekiwit/cti_research/",
                "title": "CTI Research"
            },
            "fetchDate": "2024-08-05 08:57:01.029198"
        }
    ]
}