{
    "Reddit /r/netsec": [
        {
            "entry": {
                "link": "https://www.reddit.com/r/netsec/comments/1b6qyr4/reverse_engineering_protobuf_definitions_from/",
                "title": "Reverse Engineering Protobuf Definitions From Compiled Binaries"
            },
            "fetchDate": "2024-03-05 00:56:38.056610"
        },
        {
            "entry": {
                "link": "https://www.reddit.com/r/netsec/comments/1b6rp0x/relishing_new_fickling_features_for_securing_ml/",
                "title": "Relishing new Fickling features for securing ML systems"
            },
            "fetchDate": "2024-03-05 00:56:38.056610"
        }
    ]
}