{
    "Reddit /r/netsec": [
        {
            "entry": {
                "link": "https://www.reddit.com/r/netsec/comments/1i3c7lv/finding_ssrfs_in_azure_devops/",
                "title": "Finding SSRFs in Azure DevOps"
            },
            "fetchDate": "2025-01-17 08:59:26.046854"
        },
        {
            "entry": {
                "link": "https://www.reddit.com/r/netsec/comments/1i3c2xz/bypassing_disk_encryption_on_systems_with/",
                "title": "Bypassing disk encryption on systems with automatic TPM2 unlock"
            },
            "fetchDate": "2025-01-17 08:45:29.859972"
        }
    ]
}