{
    "GoSecure Blog": [
        {
            "entry": {
                "link": "https://gosecure.ai/blog/2024/11/27/threat-hunt-of-the-month-quad7-botnet-and-password-spraying-tactics-threaten-microsoft-365-accounts/",
                "title": "Threat Hunt of the Month: Quad7 Botnet and Password Spraying Tactics Threaten Microsoft 365 Accounts"
            },
            "fetchDate": "2024-11-27 16:27:34.846144"
        }
    ],
    "InfoSec writeups": [
        {
            "entry": {
                "link": "https://infosecwriteups.com/unleashing-the-potential-of-flipper-zero-a-deep-dive-into-cyber-gadgets-a672fd1798a4?source=rss----7b722bfd1b8d---4",
                "title": "Unleashing the Potential of Flipper Zero: A Deep Dive into Cyber Gadgets"
            },
            "fetchDate": "2024-11-27 07:58:57.358823"
        },
        {
            "entry": {
                "link": "https://infosecwriteups.com/the-discovery-story-how-youtubes-logout-parameter-led-to-a-security-gap-5e144bcdfac8?source=rss----7b722bfd1b8d---4",
                "title": "The Discovery Story: How YouTube\u2019s Logout Parameter Led to a Security Gap"
            },
            "fetchDate": "2024-11-27 07:58:57.358823"
        },
        {
            "entry": {
                "link": "https://infosecwriteups.com/ssrf-to-internal-data-access-via-pdf-print-feature-b8e6a912844a?source=rss----7b722bfd1b8d---4",
                "title": "SSRF To Internal Data Access Via PDF Print Feature"
            },
            "fetchDate": "2024-11-27 07:58:57.358823"
        },
        {
            "entry": {
                "link": "https://infosecwriteups.com/how-to-build-a-strong-cybersecurity-strategy-67e235beca6e?source=rss----7b722bfd1b8d---4",
                "title": "How to Build a Strong Cybersecurity Strategy ?"
            },
            "fetchDate": "2024-11-27 07:58:57.358823"
        },
        {
            "entry": {
                "link": "https://infosecwriteups.com/reentrancy-attack-on-smart-contract-9f07335053f7?source=rss----7b722bfd1b8d---4",
                "title": "Reentrancy Attack on Smart Contract"
            },
            "fetchDate": "2024-11-27 07:58:57.358823"
        },
        {
            "entry": {
                "link": "https://infosecwriteups.com/how-i-created-an-ai-soc-analyst-f2ee2e9e86d5?source=rss----7b722bfd1b8d---4",
                "title": "How I Created an AI SOC Analyst"
            },
            "fetchDate": "2024-11-27 07:58:57.358823"
        },
        {
            "entry": {
                "link": "https://infosecwriteups.com/python-for-security-engineers-61c2cd991ab4?source=rss----7b722bfd1b8d---4",
                "title": "Python for Security Engineers"
            },
            "fetchDate": "2024-11-27 07:58:57.358823"
        },
        {
            "entry": {
                "link": "https://infosecwriteups.com/devsecops-beyond-tools-integration-4da9280c652f?source=rss----7b722bfd1b8d---4",
                "title": "DevSecOps: Beyond Tools Integration"
            },
            "fetchDate": "2024-11-27 07:58:57.358823"
        },
        {
            "entry": {
                "link": "https://infosecwriteups.com/why-small-businesses-are-prime-targets-for-cyberattacks-and-how-they-can-defend-themselves-7ae0d3e670d1?source=rss----7b722bfd1b8d---4",
                "title": "Why Small Businesses Are Prime Targets for Cyberattacks and How They Can Defend Themselves"
            },
            "fetchDate": "2024-11-27 07:58:57.358823"
        },
        {
            "entry": {
                "link": "https://infosecwriteups.com/3-way-vs-4-way-handshake-65b24ac63ca6?source=rss----7b722bfd1b8d---4",
                "title": "3 Way vs 4 Way Handshake"
            },
            "fetchDate": "2024-11-27 07:58:57.358823"
        }
    ],
    "Reddit /r/netsec": [
        {
            "entry": {
                "link": "https://www.reddit.com/r/netsec/comments/1h1apql/buskill_cables_now_available_in_a_brickandmortar/",
                "title": "BusKill cables now available in a brick-and-mortar in #TheNetherlands \ud83c\uddf3\ud83c\uddf1\ud83e\uddf1"
            },
            "fetchDate": "2024-11-27 18:14:48.609631"
        },
        {
            "entry": {
                "link": "https://www.reddit.com/r/netsec/comments/1h18g21/everyday_ghidra_ghidra_data_types_creating_custom/",
                "title": "Everyday Ghidra: Ghidra Data Types \u2014 Creating Custom GDTs From Windows Headers \u2014 Part 2"
            },
            "fetchDate": "2024-11-27 16:46:20.534975"
        },
        {
            "entry": {
                "link": "https://www.reddit.com/r/netsec/comments/1h172ab/the_hidden_network_report_how_china_unites_state/",
                "title": "The hidden network report - How China unites state, corporate, and academic assets for offensive campaigns"
            },
            "fetchDate": "2024-11-27 15:36:47.895948"
        },
        {
            "entry": {
                "link": "https://www.reddit.com/r/netsec/comments/1h112rz/new_pe_vulnerability_in_windows_os/",
                "title": "New PE Vulnerability in Windows OS!"
            },
            "fetchDate": "2024-11-27 10:14:16.233134"
        },
        {
            "entry": {
                "link": "https://www.reddit.com/r/netsec/comments/1h0zxii/mobile_scareware_now_mimics_cracked_smartphone/",
                "title": "Mobile scareware now mimics cracked smartphone screen as a result of a fake virus infection"
            },
            "fetchDate": "2024-11-27 08:54:40.139367"
        }
    ],
    "Reddit /r/websecurityresearch": [
        {
            "entry": {
                "link": "https://www.reddit.com/r/websecurityresearch/comments/1h148jb/crosssite_post_requests_without_a_contenttype/",
                "title": "Cross-Site POST Requests Without a Content-Type Header"
            },
            "fetchDate": "2024-11-27 13:41:54.818881"
        },
        {
            "entry": {
                "link": "https://www.reddit.com/r/websecurityresearch/comments/1h0zbez/turning_an_xml_file_write_into_rce_in_spring/",
                "title": "Turning an XML file write into RCE in Spring"
            },
            "fetchDate": "2024-11-27 07:58:57.358823"
        }
    ],
    "Seebug Paper": [
        {
            "entry": {
                "link": "https://paper.seebug.org/3244/",
                "title": "Android \u6076\u610f\u8f6f\u4ef6\u6df7\u6dc6\u4e0e\u5bf9\u6297\u6280\u672f\u4e13\u9898"
            },
            "fetchDate": "2024-11-27 08:25:13.289384"
        },
        {
            "entry": {
                "link": "https://paper.seebug.org/3243/",
                "title": "Prompt \u8d8a\u72f1\u624b\u518c"
            },
            "fetchDate": "2024-11-27 06:21:07.862271"
        }
    ],
    "mobile hacker": [
        {
            "entry": {
                "link": "https://www.mobile-hacker.com/2024/11/27/smartphone-scareware-cracked-screen-as-a-result-of-virus/?utm_source=rss&utm_medium=rss&utm_campaign=smartphone-scareware-cracked-screen-as-a-result-of-virus",
                "title": "Smartphone scareware: cracked screen as a result of virus"
            },
            "fetchDate": "2024-11-27 08:43:52.462474"
        }
    ]
}