{
    "Reddit /r/netsec": [
        {
            "entry": {
                "link": "https://www.reddit.com/r/netsec/comments/1fnftj8/whats_inside_the_qr_code_menu_at_this_cafe/",
                "title": "What's inside the QR code menu at this cafe?"
            },
            "fetchDate": "2024-09-23 08:46:56.038634"
        },
        {
            "entry": {
                "link": "https://www.reddit.com/r/netsec/comments/1fnfdgk/open_to_exploitation_the_security_risks_of/",
                "title": "Open to Exploitation: The Security Risks of Unauthenticated Pager Networks"
            },
            "fetchDate": "2024-09-23 08:29:35.953044"
        }
    ]
}