{
    "InfoSec writeups": [
        {
            "entry": {
                "link": "https://infosecwriteups.com/cisa-sounds-the-alarm-broadcom-and-commvault-flaws-under-active-exploitation-%EF%B8%8F-67a3c5f7f3dd?source=rss----7b722bfd1b8d---4",
                "title": "CISA Sounds the Alarm: Broadcom and Commvault Flaws Under Active Exploitation! \ufe0f"
            },
            "fetchDate": "2025-04-30 06:27:28.429855"
        },
        {
            "entry": {
                "link": "https://infosecwriteups.com/what-recruiters-look-for-in-a-cybersecurity-resume-in-2025-dcc81fa3154e?source=rss----7b722bfd1b8d---4",
                "title": "What Recruiters Look for in a Cybersecurity Resume in 2025"
            },
            "fetchDate": "2025-04-30 06:27:28.429855"
        },
        {
            "entry": {
                "link": "https://infosecwriteups.com/500-bug-bounty-open-redirection-via-oauth-on-shopify-4159387482f9?source=rss----7b722bfd1b8d---4",
                "title": "$500 Bug Bounty:Open Redirection via OAuth on Shopify"
            },
            "fetchDate": "2025-04-30 06:27:28.429855"
        },
        {
            "entry": {
                "link": "https://infosecwriteups.com/how-to-build-a-cyber-threat-intelligence-collection-plan-ed36715f7f33?source=rss----7b722bfd1b8d---4",
                "title": "How to Build a Cyber Threat Intelligence Collection Plan"
            },
            "fetchDate": "2025-04-30 06:27:28.429855"
        },
        {
            "entry": {
                "link": "https://infosecwriteups.com/overpass-2-hacked-walkthrough-40c96d21c69b?source=rss----7b722bfd1b8d---4",
                "title": "Overpass 2\u200a\u2014\u200aHacked Walkthrough"
            },
            "fetchDate": "2025-04-30 06:27:28.429855"
        },
        {
            "entry": {
                "link": "https://infosecwriteups.com/1-click-account-takeover-xss-cors-misconfiguration-jwt-forgery-0cf73a28e236?source=rss----7b722bfd1b8d---4",
                "title": "1 Click Account Takeover | XSS | CORS Misconfiguration | JWT Forgery"
            },
            "fetchDate": "2025-04-30 06:27:28.429855"
        },
        {
            "entry": {
                "link": "https://infosecwriteups.com/unlock-bounties-by-simply-reading-a-smart-way-to-earn-63a1cb410450?source=rss----7b722bfd1b8d---4",
                "title": "Unlock Bounties by Simply Reading: A Smart Way to Earn"
            },
            "fetchDate": "2025-04-30 06:27:28.429855"
        },
        {
            "entry": {
                "link": "https://infosecwriteups.com/top-10-cybersecurity-blog-posts-that-made-april-2025-a-breakthrough-month-for-openexploit-fd21830fdd93?source=rss----7b722bfd1b8d---4",
                "title": "Top 10 Cybersecurity Blog Posts That Made April 2025 a Breakthrough Month for OpenExploit"
            },
            "fetchDate": "2025-04-30 06:27:28.429855"
        },
        {
            "entry": {
                "link": "https://infosecwriteups.com/from-sql-injection-to-weak-passwords-a-deep-dive-into-a-tamil-nadu-government-security-flaw-1b648d62d457?source=rss----7b722bfd1b8d---4",
                "title": "From SQL Injection to Weak Passwords : A Deep Dive into a Tamil Nadu Government Security Flaw"
            },
            "fetchDate": "2025-04-30 06:27:28.429855"
        },
        {
            "entry": {
                "link": "https://infosecwriteups.com/how-i-found-bugs-on-adobe-16cedb79e830?source=rss----7b722bfd1b8d---4",
                "title": "How I Found Bugs on Adobe"
            },
            "fetchDate": "2025-04-30 06:27:28.429855"
        }
    ],
    "Reddit /r/netsec": [
        {
            "entry": {
                "link": "https://www.reddit.com/r/netsec/comments/1kbc6vd/samsung_magicinfo_unauthenticated_rce/",
                "title": "Samsung MagicINFO Unauthenticated RCE"
            },
            "fetchDate": "2025-04-30 09:36:08.449672"
        },
        {
            "entry": {
                "link": "https://www.reddit.com/r/netsec/comments/1kbbu88/a_technical_review_of_aiinfraguard_v2_new_mcp/",
                "title": "A Technical Review of AI-Infra-Guard V2: New MCP Server Security Analysis Tool"
            },
            "fetchDate": "2025-04-30 08:59:01.106491"
        },
        {
            "entry": {
                "link": "https://www.reddit.com/r/netsec/comments/1kb7lx6/gfi_mailessentials_yet_another_net_target_frycos/",
                "title": "GFI MailEssentials - Yet Another .NET Target - Frycos"
            },
            "fetchDate": "2025-04-30 04:11:47.431431"
        }
    ]
}