{
    "InfoSec writeups": [
        {
            "entry": {
                "link": "https://infosecwriteups.com/i-followed-the-password-reset-flow-and-ended-up-resetting-everyones-password-d81e07e6e3b7?source=rss----7b722bfd1b8d---4",
                "title": "I Followed the Password Reset Flow\u200a\u2014\u200aand Ended Up Resetting Everyone\u2019s Password"
            },
            "fetchDate": "2026-02-04 15:10:16.696185"
        },
        {
            "entry": {
                "link": "https://infosecwriteups.com/how-to-hack-swagger-ui-complete-guide-9291d9158603?source=rss----7b722bfd1b8d---4",
                "title": "How to Hack Swagger UI Complete Guide."
            },
            "fetchDate": "2026-02-04 15:10:16.696185"
        },
        {
            "entry": {
                "link": "https://infosecwriteups.com/as-always-in-every-penetration-testing-engagements-we-start-by-reconnaissance-and-information-04bf8744dc7e?source=rss----7b722bfd1b8d---4",
                "title": "Proving Grounds Linux lab Levram ( Road to OSCP )"
            },
            "fetchDate": "2026-02-04 15:10:16.696185"
        }
    ],
    "Reddit /r/netsec": [
        {
            "entry": {
                "link": "https://www.reddit.com/r/netsec/comments/1qvgylo/my_book_is_about_a_corporate_it_analyst_who_gets/",
                "title": "My book is about a corporate IT analyst who gets caught up in an illegal debt collection scheme through an anonymized encrypted device. It\u2019s currently free on Amazon for educational purposes"
            },
            "fetchDate": "2026-02-04 07:07:38.391563"
        }
    ]
}