{
    "InfoSec writeups": [
        {
            "entry": {
                "link": "https://infosecwriteups.com/windows-xp-is-hackable-or-nah-lets-test-that-6201f943c2af?source=rss----7b722bfd1b8d---4",
                "title": "Windows XP is Hackable or Nah? Let\u2019s Test That!"
            },
            "fetchDate": "2025-02-05 06:36:42.969945"
        },
        {
            "entry": {
                "link": "https://infosecwriteups.com/brute-forcing-financial-apps-with-hackerone-86e22add374e?source=rss----7b722bfd1b8d---4",
                "title": "Brute Forcing Financial Apps With HackerOne"
            },
            "fetchDate": "2025-02-05 06:15:48.955261"
        },
        {
            "entry": {
                "link": "https://infosecwriteups.com/pii-exposure-the-data-heist-you-never-knew-was-possible-5577b84a1074?source=rss----7b722bfd1b8d---4",
                "title": "PII Exposure: The Data Heist You Never Knew Was Possible!"
            },
            "fetchDate": "2025-02-05 06:15:48.955261"
        },
        {
            "entry": {
                "link": "https://infosecwriteups.com/how-i-made-top-edr-tools-look-like-clueless-babysitters-using-just-notepad-pure-chaos-f852463f5149?source=rss----7b722bfd1b8d---4",
                "title": "How I Made Top EDR Tools Look Like Clueless Babysitters (Using Just Notepad & Pure Chaos)"
            },
            "fetchDate": "2025-02-05 06:15:48.955261"
        },
        {
            "entry": {
                "link": "https://infosecwriteups.com/xss-bypassing-waf-with-hex-overflow-bafbf8bc43b0?source=rss----7b722bfd1b8d---4",
                "title": "XSS\u200a\u2014\u200aBypassing WAF with Hex Overflow"
            },
            "fetchDate": "2025-02-05 06:15:48.955261"
        },
        {
            "entry": {
                "link": "https://infosecwriteups.com/paginator-v2-nullcon-ctf-2025-7bc5f8f445b4?source=rss----7b722bfd1b8d---4",
                "title": "Paginator v2- NullCon CTF 2025"
            },
            "fetchDate": "2025-02-05 06:15:48.955261"
        }
    ],
    "Reddit /r/netsec": [
        {
            "entry": {
                "link": "https://www.reddit.com/r/netsec/comments/1ii16vd/certificate_transparency_is_now_enforced_in/",
                "title": "Certificate Transparency is now enforced in Firefox on desktop platforms starting with version 135"
            },
            "fetchDate": "2025-02-05 03:50:59.255147"
        }
    ],
    "mobile hacker": [
        {
            "entry": {
                "link": "https://www.mobile-hacker.com/2025/02/05/hacking-on-the-go-wi-fi-karma-attacks-with-mobile-devices/?utm_source=rss&utm_medium=rss&utm_campaign=hacking-on-the-go-wi-fi-karma-attacks-with-mobile-devices",
                "title": "Hacking on the Go: Wi-Fi Karma Attacks with Mobile Devices"
            },
            "fetchDate": "2025-02-05 07:29:19.633544"
        }
    ]
}