{
    "InfoSec writeups": [
        {
            "entry": {
                "link": "https://infosecwriteups.com/when-i-bypassed-google-captcha-the-epic-exploit-of-post-based-xss-csrf-1fb66f7cf886?source=rss----7b722bfd1b8d---4",
                "title": "When I Bypassed Google CAPTCHA: The Epic Exploit of POST-based XSS + CSRF"
            },
            "fetchDate": "2025-01-31 10:33:34.629568"
        },
        {
            "entry": {
                "link": "https://infosecwriteups.com/how-i-earned-200-using-github-dorking-a-manual-and-automated-guide-to-finding-sensitive-ebbbfcad7296?source=rss----7b722bfd1b8d---4",
                "title": "How I Earned $200 Using GitHub Dorking: A Manual and Automated Guide to Finding Sensitive\u2026"
            },
            "fetchDate": "2025-01-31 10:16:42.429886"
        },
        {
            "entry": {
                "link": "https://infosecwriteups.com/wi-fi-hacking-4d9aa3ded7fd?source=rss----7b722bfd1b8d---4",
                "title": "Step-by-Step Complete Beginners guide of Wi-Fi Hacking"
            },
            "fetchDate": "2025-01-31 10:16:42.429886"
        },
        {
            "entry": {
                "link": "https://infosecwriteups.com/my-bug-bounty-journey-a-middle-class-kids-quest-for-free-and-beyond-1cd6b65240d6?source=rss----7b722bfd1b8d---4",
                "title": "My Bug Bounty Journey: A Middle-Class Kid\u2019s Quest for Free and Beyond"
            },
            "fetchDate": "2025-01-31 10:16:42.429886"
        }
    ],
    "Reddit /r/netsec": [
        {
            "entry": {
                "link": "https://www.reddit.com/r/netsec/comments/1iean5l/crlf_injection_via_tryaddwithoutvalidation_in_net/",
                "title": "CRLF injection via TryAddWithoutValidation in .NET"
            },
            "fetchDate": "2025-01-31 08:58:53.676302"
        }
    ]
}